ursinaxball/__init__.py
ursinaxball/common_values.py
ursinaxball/game.py
ursinaxball/modules/__init__.py
ursinaxball/modules/bots/__init__.py
ursinaxball/modules/bots/advanced_bots.py
ursinaxball/modules/bots/bot.py
ursinaxball/modules/bots/common_bots.py
ursinaxball/modules/physics/__init__.py
ursinaxball/modules/physics/fn_base.py
ursinaxball/modules/physics/physics_handler.py
ursinaxball/modules/player/__init__.py
ursinaxball/modules/player/player_data.py
ursinaxball/modules/player/player_handler.py
ursinaxball/modules/systems/__init__.py
ursinaxball/modules/systems/game_recorder.py
ursinaxball/modules/systems/game_renderer.py
ursinaxball/modules/systems/game_score.py
ursinaxball/objects/__init__.py
ursinaxball/objects/base/__init__.py
ursinaxball/objects/base/background_object.py
ursinaxball/objects/base/ball_physics.py
ursinaxball/objects/base/disc_object.py
ursinaxball/objects/base/goal_object.py
ursinaxball/objects/base/physics_object.py
ursinaxball/objects/base/plane_object.py
ursinaxball/objects/base/player_physics.py
ursinaxball/objects/base/segment_object.py
ursinaxball/objects/base/trait_object.py
ursinaxball/objects/base/vertex_object.py
ursinaxball/objects/stadium_object.py
ursinaxball/stadiums/__init__.py
ursinaxball/stadiums/big.json5
ursinaxball/stadiums/classic.json5
ursinaxball/stadiums/futsal-big.json5
ursinaxball/stadiums/futsal-classic.json5
ursinaxball/stadiums/obstacle-map-winky.json5
ursinaxball/stadiums/penalty-soccer.json5
ursinaxball/stadiums/rounded.json5
ursinaxball-0.2.4.dist-info/METADATA
ursinaxball-0.2.4.dist-info/WHEEL
ursinaxball-0.2.4.dist-info/RECORD
